examples/masm/ops/unary_ops.sv
module UnaryOps(
    input [3:0] a,
    output[3:0] not_,
    output [3:0] pos_,
    output [3:0] neg_,

    output [5:0] not_w,
    output [5:0] pos_w,
    output [5:0] neg_w,


    output[3:0] not_signed,
    output [3:0] pos_signed,
    output [3:0] neg_signed,

    output[5:0] not_signed_w,
    output [5:0] pos_signed_w,
    output [5:0] neg_signed_w,

    output [3:0] reduce_and_,
    output [3:0] reduce_or_,
    output [3:0] reduce_xor_,
    output [3:0] reduce_xnor_,
    output [3:0] reduce_bool_,
    output [3:0] logic_not_,

    output [3:0] reduce_and_signed,
    output [3:0] reduce_or_signed,
    output [3:0] reduce_xor_signed,
    output [3:0] reduce_xnor_signed,
    output [3:0] reduce_bool_signed,
    output [3:0] logic_not_signed,

    output [0:0] reduce_and_bit,
    output [0:0] reduce_or_bit,
    output [0:0] reduce_xor_bit,
    output [0:0] reduce_xnor_bit,
    output [0:0] reduce_bool_bit,
    output [0:0] logic_not_bit,


    output [0:0] reduce_xor_bit_bit,
    output [0:0] reduce_xnor_bit_bit
    );

    assign not_ = ~a;
    assign pos_ = +a;
    assign neg_ = -a;

    assign not_w = ~a;
    assign pos_w = +a;
    assign neg_w = -a;


    assign not_signed = ~$signed(a);
    assign pos_signed = +$signed(a);
    assign neg_signed = -$signed(a);

    assign not_signed_w = ~$signed(a);
    assign pos_signed_w = +$signed(a);
    assign neg_signed_w = -$signed(a);

    assign reduce_and_ = &a;
    assign reduce_or_ = |a;
    assign reduce_xor_ = ^a;
    assign reduce_xnor_ = ~^a;
    assign reduce_bool_ = a ? 1'b1 : 1'b0;
    assign logic_not_ = !a ? 1'b1 : 1'b0;


    assign reduce_and_signed = &$signed(a);
    assign reduce_or_signed = |$signed(a);
    assign reduce_xor_signed = ^$signed(a);
    assign reduce_xnor_signed = ~^$signed(a);
    assign reduce_bool_signed = $signed(a) ? 1'b1 : 1'b0;
    assign logic_not_signed = !$signed(a) ? 1'b1 : 1'b0;

    assign reduce_and_bit = &a;
    assign reduce_or_bit = |a;
    assign reduce_xor_bit = ^a;
    assign reduce_xnor_bit = ~^a;
    assign reduce_bool_bit = a ? 1'b1 : 1'b0;
    assign logic_not_bit = !a ? 1'b1 : 1'b0;


    assign reduce_xor_bit_bit = ^a[0];
    assign reduce_xnor_bit_bit = ~^a[0];

endmodule

examples/masm/unary_ops_tb.v
`ifndef outfile
	`define outfile "/dev/stdout"
`endif
module testbench;

integer i;
integer file;

reg [1023:0] filename;

reg [31:0] xorshift128_x = 123456789;
reg [31:0] xorshift128_y = 362436069;
reg [31:0] xorshift128_z = 521288629;
reg [31:0] xorshift128_w = 1652613690; // <-- seed value
reg [31:0] xorshift128_t;

task xorshift128;
begin
	xorshift128_t = xorshift128_x ^ (xorshift128_x << 11);
	xorshift128_x = xorshift128_y;
	xorshift128_y = xorshift128_z;
	xorshift128_z = xorshift128_w;
	xorshift128_w = xorshift128_w ^ (xorshift128_w >> 19) ^ xorshift128_t ^ (xorshift128_t >> 8);
end
endtask

reg [3:0] sig_UnaryOps_a;
wire [3:0] sig_UnaryOps_logic_not_;
wire [0:0] sig_UnaryOps_logic_not_bit;
wire [3:0] sig_UnaryOps_logic_not_signed;
wire [3:0] sig_UnaryOps_neg_;
wire [3:0] sig_UnaryOps_neg_signed;
wire [5:0] sig_UnaryOps_neg_signed_w;
wire [5:0] sig_UnaryOps_neg_w;
wire [3:0] sig_UnaryOps_not_;
wire [3:0] sig_UnaryOps_not_signed;
wire [5:0] sig_UnaryOps_not_signed_w;
wire [5:0] sig_UnaryOps_not_w;
wire [3:0] sig_UnaryOps_pos_;
wire [3:0] sig_UnaryOps_pos_signed;
wire [5:0] sig_UnaryOps_pos_signed_w;
wire [5:0] sig_UnaryOps_pos_w;
wire [3:0] sig_UnaryOps_reduce_and_;
wire [0:0] sig_UnaryOps_reduce_and_bit;
wire [3:0] sig_UnaryOps_reduce_and_signed;
wire [3:0] sig_UnaryOps_reduce_bool_;
wire [0:0] sig_UnaryOps_reduce_bool_bit;
wire [3:0] sig_UnaryOps_reduce_bool_signed;
wire [3:0] sig_UnaryOps_reduce_or_;
wire [0:0] sig_UnaryOps_reduce_or_bit;
wire [3:0] sig_UnaryOps_reduce_or_signed;
wire [3:0] sig_UnaryOps_reduce_xnor_;
wire [0:0] sig_UnaryOps_reduce_xnor_bit;
wire [0:0] sig_UnaryOps_reduce_xnor_bit_bit;
wire [3:0] sig_UnaryOps_reduce_xnor_signed;
wire [3:0] sig_UnaryOps_reduce_xor_;
wire [0:0] sig_UnaryOps_reduce_xor_bit;
wire [0:0] sig_UnaryOps_reduce_xor_bit_bit;
wire [3:0] sig_UnaryOps_reduce_xor_signed;
UnaryOps uut_UnaryOps(
	.a(sig_UnaryOps_a),
	.logic_not_(sig_UnaryOps_logic_not_),
	.logic_not_bit(sig_UnaryOps_logic_not_bit),
	.logic_not_signed(sig_UnaryOps_logic_not_signed),
	.neg_(sig_UnaryOps_neg_),
	.neg_signed(sig_UnaryOps_neg_signed),
	.neg_signed_w(sig_UnaryOps_neg_signed_w),
	.neg_w(sig_UnaryOps_neg_w),
	.not_(sig_UnaryOps_not_),
	.not_signed(sig_UnaryOps_not_signed),
	.not_signed_w(sig_UnaryOps_not_signed_w),
	.not_w(sig_UnaryOps_not_w),
	.pos_(sig_UnaryOps_pos_),
	.pos_signed(sig_UnaryOps_pos_signed),
	.pos_signed_w(sig_UnaryOps_pos_signed_w),
	.pos_w(sig_UnaryOps_pos_w),
	.reduce_and_(sig_UnaryOps_reduce_and_),
	.reduce_and_bit(sig_UnaryOps_reduce_and_bit),
	.reduce_and_signed(sig_UnaryOps_reduce_and_signed),
	.reduce_bool_(sig_UnaryOps_reduce_bool_),
	.reduce_bool_bit(sig_UnaryOps_reduce_bool_bit),
	.reduce_bool_signed(sig_UnaryOps_reduce_bool_signed),
	.reduce_or_(sig_UnaryOps_reduce_or_),
	.reduce_or_bit(sig_UnaryOps_reduce_or_bit),
	.reduce_or_signed(sig_UnaryOps_reduce_or_signed),
	.reduce_xnor_(sig_UnaryOps_reduce_xnor_),
	.reduce_xnor_bit(sig_UnaryOps_reduce_xnor_bit),
	.reduce_xnor_bit_bit(sig_UnaryOps_reduce_xnor_bit_bit),
	.reduce_xnor_signed(sig_UnaryOps_reduce_xnor_signed),
	.reduce_xor_(sig_UnaryOps_reduce_xor_),
	.reduce_xor_bit(sig_UnaryOps_reduce_xor_bit),
	.reduce_xor_bit_bit(sig_UnaryOps_reduce_xor_bit_bit),
	.reduce_xor_signed(sig_UnaryOps_reduce_xor_signed)
);

task UnaryOps_reset;
begin
	sig_UnaryOps_a <= #2 0;
	#100;
	sig_UnaryOps_a <= #2 ~0;
	#100;
	#0;
end
endtask

task UnaryOps_update_data;
begin
	xorshift128;
	sig_UnaryOps_a <= #2 { xorshift128_x, xorshift128_y, xorshift128_z, xorshift128_w };
	#100;
end
endtask

task UnaryOps_update_clock;
begin
end
endtask

task UnaryOps_print_status;
begin
	$fdisplay(file, "#OUT# %b %b %b %t %d", { sig_UnaryOps_a }, { 1'bx }, { sig_UnaryOps_logic_not_, sig_UnaryOps_logic_not_bit, sig_UnaryOps_logic_not_signed, sig_UnaryOps_neg_, sig_UnaryOps_neg_signed, sig_UnaryOps_neg_signed_w, sig_UnaryOps_neg_w, sig_UnaryOps_not_, sig_UnaryOps_not_signed, sig_UnaryOps_not_signed_w, sig_UnaryOps_not_w, sig_UnaryOps_pos_, sig_UnaryOps_pos_signed, sig_UnaryOps_pos_signed_w, sig_UnaryOps_pos_w, sig_UnaryOps_reduce_and_, sig_UnaryOps_reduce_and_bit, sig_UnaryOps_reduce_and_signed, sig_UnaryOps_reduce_bool_, sig_UnaryOps_reduce_bool_bit, sig_UnaryOps_reduce_bool_signed, sig_UnaryOps_reduce_or_, sig_UnaryOps_reduce_or_bit, sig_UnaryOps_reduce_or_signed, sig_UnaryOps_reduce_xnor_, sig_UnaryOps_reduce_xnor_bit, sig_UnaryOps_reduce_xnor_bit_bit, sig_UnaryOps_reduce_xnor_signed, sig_UnaryOps_reduce_xor_, sig_UnaryOps_reduce_xor_bit, sig_UnaryOps_reduce_xor_bit_bit, sig_UnaryOps_reduce_xor_signed }, $time, i);
end
endtask

task UnaryOps_print_header;
begin
	$fdisplay(file, "#OUT#");
	$fdisplay(file, "#OUT#   A   sig_UnaryOps_a");
	$fdisplay(file, "#OUT#   B   sig_UnaryOps_logic_not_");
	$fdisplay(file, "#OUT#   C   sig_UnaryOps_logic_not_bit");
	$fdisplay(file, "#OUT#   D   sig_UnaryOps_logic_not_signed");
	$fdisplay(file, "#OUT#   E   sig_UnaryOps_neg_");
	$fdisplay(file, "#OUT#   F   sig_UnaryOps_neg_signed");
	$fdisplay(file, "#OUT#   G   sig_UnaryOps_neg_signed_w");
	$fdisplay(file, "#OUT#   H   sig_UnaryOps_neg_w");
	$fdisplay(file, "#OUT#   I   sig_UnaryOps_not_");
	$fdisplay(file, "#OUT#   J   sig_UnaryOps_not_signed");
	$fdisplay(file, "#OUT#   K   sig_UnaryOps_not_signed_w");
	$fdisplay(file, "#OUT#   L   sig_UnaryOps_not_w");
	$fdisplay(file, "#OUT#   M   sig_UnaryOps_pos_");
	$fdisplay(file, "#OUT#   N   sig_UnaryOps_pos_signed");
	$fdisplay(file, "#OUT#   O   sig_UnaryOps_pos_signed_w");
	$fdisplay(file, "#OUT#   P   sig_UnaryOps_pos_w");
	$fdisplay(file, "#OUT#   Q   sig_UnaryOps_reduce_and_");
	$fdisplay(file, "#OUT#   R   sig_UnaryOps_reduce_and_bit");
	$fdisplay(file, "#OUT#   S   sig_UnaryOps_reduce_and_signed");
	$fdisplay(file, "#OUT#   T   sig_UnaryOps_reduce_bool_");
	$fdisplay(file, "#OUT#   U   sig_UnaryOps_reduce_bool_bit");
	$fdisplay(file, "#OUT#   V   sig_UnaryOps_reduce_bool_signed");
	$fdisplay(file, "#OUT#   W   sig_UnaryOps_reduce_or_");
	$fdisplay(file, "#OUT#   X   sig_UnaryOps_reduce_or_bit");
	$fdisplay(file, "#OUT#   Y   sig_UnaryOps_reduce_or_signed");
	$fdisplay(file, "#OUT#   Z   sig_UnaryOps_reduce_xnor_");
	$fdisplay(file, "#OUT#   A   sig_UnaryOps_reduce_xnor_bit");
	$fdisplay(file, "#OUT#   B   sig_UnaryOps_reduce_xnor_bit_bit");
	$fdisplay(file, "#OUT#   C   sig_UnaryOps_reduce_xnor_signed");
	$fdisplay(file, "#OUT#   D   sig_UnaryOps_reduce_xor_");
	$fdisplay(file, "#OUT#   E   sig_UnaryOps_reduce_xor_bit");
	$fdisplay(file, "#OUT#   F   sig_UnaryOps_reduce_xor_bit_bit");
	$fdisplay(file, "#OUT#   G   sig_UnaryOps_reduce_xor_signed");
	$fdisplay(file, "#OUT#");
	$fdisplay(file, {"#OUT# ", "/--A", " ", "#", " ", "/--B", "C", "/--D", "/--E", "/--F", "/----G", "/----H", "/--I", "/--J", "/----K", "/----L", "/--M", "/--N", "/----O", "/----P", "/--Q", "R", "/--S", "/--T", "U", "/--V", "/--W", "X", "/--Y", "/--Z", "A", "B", "/--C", "/--D", "E", "F", "/--G"});
end
endtask

task UnaryOps_test;
begin
	$fdisplay(file, "#OUT#\n#OUT# ==== UnaryOps ====");
	UnaryOps_reset;
	for (i=0; i<1000; i=i+1) begin
		if (i % 20 == 0) UnaryOps_print_header;
		#100; UnaryOps_update_data;
		#100; UnaryOps_update_clock;
		#100; UnaryOps_print_status;
	end
end
endtask

initial begin
	if ($value$plusargs("VCD=%s", filename)) begin
		$dumpfile(filename);
		$dumpvars(0, testbench);
	end
	if ($value$plusargs("OUT=%s", filename)) begin
		file = $fopen(filename);
	end else begin
		file = $fopen(`outfile);
	end
	UnaryOps_test;
	$fclose(file);
	$finish;
end

endmodule

examples/masm/unary_ops.vcd
$date
	Sun May 15 13:21:38 2022
$end
$version
	Icarus Verilog
$end
$timescale
	1s
$end
$scope module testbench $end
$var wire 4 ! sig_UnaryOps_pos_signed [3:0] $end
$var wire 4 " sig_UnaryOps_reduce_xor_signed [3:0] $end
$var wire 1 # sig_UnaryOps_reduce_xor_bit_bit $end
$var wire 1 $ sig_UnaryOps_reduce_xor_bit $end
$var wire 4 % sig_UnaryOps_reduce_xor_ [3:0] $end
$var wire 4 & sig_UnaryOps_reduce_xnor_signed [3:0] $end
$var wire 1 ' sig_UnaryOps_reduce_xnor_bit_bit $end
$var wire 1 ( sig_UnaryOps_reduce_xnor_bit $end
$var wire 4 ) sig_UnaryOps_reduce_xnor_ [3:0] $end
$var wire 4 * sig_UnaryOps_reduce_or_signed [3:0] $end
$var wire 1 + sig_UnaryOps_reduce_or_bit $end
$var wire 4 , sig_UnaryOps_reduce_or_ [3:0] $end
$var wire 4 - sig_UnaryOps_reduce_bool_signed [3:0] $end
$var wire 1 . sig_UnaryOps_reduce_bool_bit $end
$var wire 4 / sig_UnaryOps_reduce_bool_ [3:0] $end
$var wire 4 0 sig_UnaryOps_reduce_and_signed [3:0] $end
$var wire 1 1 sig_UnaryOps_reduce_and_bit $end
$var wire 4 2 sig_UnaryOps_reduce_and_ [3:0] $end
$var wire 6 3 sig_UnaryOps_pos_w [5:0] $end
$var wire 6 4 sig_UnaryOps_pos_signed_w [5:0] $end
$var wire 4 5 sig_UnaryOps_pos_ [3:0] $end
$var wire 6 6 sig_UnaryOps_not_w [5:0] $end
$var wire 6 7 sig_UnaryOps_not_signed_w [5:0] $end
$var wire 4 8 sig_UnaryOps_not_signed [3:0] $end
$var wire 4 9 sig_UnaryOps_not_ [3:0] $end
$var wire 6 : sig_UnaryOps_neg_w [5:0] $end
$var wire 6 ; sig_UnaryOps_neg_signed_w [5:0] $end
$var wire 4 < sig_UnaryOps_neg_signed [3:0] $end
$var wire 4 = sig_UnaryOps_neg_ [3:0] $end
$var wire 4 > sig_UnaryOps_logic_not_signed [3:0] $end
$var wire 1 ? sig_UnaryOps_logic_not_bit $end
$var wire 4 @ sig_UnaryOps_logic_not_ [3:0] $end
$var reg 1024 A filename [1023:0] $end
$var reg 4 B sig_UnaryOps_a [3:0] $end
$var reg 32 C xorshift128_t [31:0] $end
$var reg 32 D xorshift128_w [31:0] $end
$var reg 32 E xorshift128_x [31:0] $end
$var reg 32 F xorshift128_y [31:0] $end
$var reg 32 G xorshift128_z [31:0] $end
$var integer 32 H file [31:0] $end
$var integer 32 I i [31:0] $end
$scope module uut_UnaryOps $end
$var wire 4 J a [3:0] $end
$var wire 4 K not_ [3:0] $end
$var wire 4 L not_signed [3:0] $end
$var wire 6 M not_signed_w [5:0] $end
$var wire 6 N not_w [5:0] $end
$var wire 4 O pos_ [3:0] $end
$var wire 4 P pos_signed [3:0] $end
$var wire 4 Q reduce_xor_signed [3:0] $end
$var wire 1 # reduce_xor_bit_bit $end
$var wire 1 $ reduce_xor_bit $end
$var wire 4 R reduce_xor_ [3:0] $end
$var wire 4 S reduce_xnor_signed [3:0] $end
$var wire 1 ' reduce_xnor_bit_bit $end
$var wire 1 ( reduce_xnor_bit $end
$var wire 4 T reduce_xnor_ [3:0] $end
$var wire 4 U reduce_or_signed [3:0] $end
$var wire 1 + reduce_or_bit $end
$var wire 4 V reduce_or_ [3:0] $end
$var wire 4 W reduce_bool_signed [3:0] $end
$var wire 1 . reduce_bool_bit $end
$var wire 4 X reduce_bool_ [3:0] $end
$var wire 4 Y reduce_and_signed [3:0] $end
$var wire 1 1 reduce_and_bit $end
$var wire 4 Z reduce_and_ [3:0] $end
$var wire 6 [ pos_w [5:0] $end
$var wire 6 \ pos_signed_w [5:0] $end
$var wire 6 ] neg_w [5:0] $end
$var wire 6 ^ neg_signed_w [5:0] $end
$var wire 4 _ neg_signed [3:0] $end
$var wire 4 ` neg_ [3:0] $end
$var wire 4 a logic_not_signed [3:0] $end
$var wire 1 ? logic_not_bit $end
$var wire 4 b logic_not_ [3:0] $end
$upscope $end
$scope task UnaryOps_print_header $end
$upscope $end
$scope task UnaryOps_print_status $end
$upscope $end
$scope task UnaryOps_reset $end
$upscope $end
$scope task UnaryOps_test $end
$upscope $end
$scope task UnaryOps_update_clock $end
$upscope $end
$scope task UnaryOps_update_data $end
$upscope $end
$scope task xorshift128 $end
$upscope $end
$upscope $end
$enddefinitions $end
#0
$dumpvars
b0x b
b0x a
bx `
bx _
bx ^
bx ]
bx \
b0xxxx [
b0x Z
b0x Y
b0x X
b0x W
b0x V
b0x U
b0x T
b0x S
b0x R
b0x Q
bx P
bx O
b11xxxx N
bx M
bx L
bx K
bx J
bx I
b10 H
b11111000100100011101110110101 G
b10101100110100101010111100101 F
b111010110111100110100010101 E
b1100010100000001110001000111010 D
bx C
bx B
b1110101011011100110000101110010011110010101111101101111011100000111001100101110011101100110001101100100 A
b0x @
x?
b0x >
bx =
bx <
bx ;
bx :
bx 9
bx 8
bx 7
b11xxxx 6
bx 5
bx 4
b0xxxx 3
b0x 2
x1
b0x 0
b0x /
x.
b0x -
b0x ,
x+
b0x *
b0x )
x(
x'
b0x &
b0x %
x$
x#
b0x "
bx !
$end
#2
b1111 9
b1111 K
b1111 8
b1111 L
b111111 6
b111111 N
b111111 7
b111111 M
b0 /
b0 X
b1 @
b1 b
b0 -
b0 W
b1 >
b1 a
0.
1?
0#
1'
b0 5
b0 O
b0 =
b0 `
b0 3
b0 [
b0 :
b0 ]
b0 <
b0 _
b0 4
b0 \
b0 ;
b0 ^
b0 2
b0 Z
b0 ,
b0 V
b0 %
b0 R
b1 )
b1 T
b0 0
b0 Y
b0 *
b0 U
b0 "
b0 Q
b1 &
b1 S
01
0+
0$
1(
b0 !
b0 B
b0 J
b0 P
#102
b0 9
b0 K
b0 8
b0 L
b110000 6
b110000 N
b0 7
b0 M
b1 /
b1 X
b0 @
b0 b
b1 -
b1 W
b0 >
b0 a
1.
0?
1#
0'
b1111 5
b1111 O
b1 =
b1 `
b1111 3
b1111 [
b110001 :
b110001 ]
b1 <
b1 _
b111111 4
b111111 \
b1 ;
b1 ^
b1 2
b1 Z
b1 ,
b1 V
b1 0
b1 Y
b1 *
b1 U
11
1+
b1111 !
b1111 B
b1111 J
b1111 P
#200
b0 I
#300
b10111011011010101011100000011010 D
b1100010100000001110001000111010 G
b11111000100100011101110110101 F
b10101100110100101010111100101 E
b11011001001100110110010100010101 C
#302
b101 9
b101 K
b101 8
b101 L
b110101 6
b110101 N
b101 7
b101 M
0#
1'
b1010 5
b1010 O
b110 =
b110 `
b1010 3
b1010 [
b110110 :
b110110 ]
b110 <
b110 _
b111010 4
b111010 \
b110 ;
b110 ^
b0 2
b0 Z
b0 0
b0 Y
01
b1010 !
b1010 B
b1010 J
b1010 P
#600
b1 I
#700
b1111100100110001110011111101111 D
b10111011011010101011100000011010 G
b1100010100000001110001000111010 F
b11111000100100011101110110101 E
b11000111001101010111110111100101 C
#702
b0 9
b0 K
b0 8
b0 L
b110000 6
b110000 N
b0 7
b0 M
1#
0'
b1111 5
b1111 O
b1 =
b1 `
b1111 3
b1111 [
b110001 :
b110001 ]
b1 <
b1 _
b111111 4
b111111 \
b1 ;
b1 ^
b1 2
b1 Z
b1 0
b1 Y
11
b1111 !
b1111 B
b1111 J
b1111 P
#1000
b10 I
#1100
b11110010110110011011010001011010 D
b1111100100110001110011111101111 G
b10111011011010101011100000011010 F
b1100010100000001110001000111010 E
b10001110110011111001001110110101 C
#1102
b101 9
b101 K
b101 8
b101 L
b110101 6
b110101 N
b101 7
b101 M
0#
1'
b1010 5
b1010 O
b110 =
b110 `
b1010 3
b1010 [
b110110 :
b110110 ]
b110 <
b110 _
b111010 4
b111010 \
b110 ;
b110 ^
b0 2
b0 Z
b0 0
b0 Y
01
b1010 !
b1010 B
b1010 J
b1010 P
#1400
b11 I
#1500
b10010111001011010000100100001001 D
b11110010110110011011010001011010 G
b1111100100110001110011111101111 F
b10111011011010101011100000011010 E
b1100101100100010011001000111010 C
#1502
b110 9
b110 K
b110 8
b110 L
b110110 6
b110110 N
b110 7
b110 M
1#
0'
b1001 5
b1001 O
b111 =
b111 `
b1001 3
b1001 [
b110111 :
b110111 ]
b111 <
b111 _
b111001 4
b111001 \
b111 ;
b111 ^
b1001 !
b1001 B
b1001 J
b1001 P
#1800
b100 I
#1900
b1111001011010011101100110011110 D
b10010111001011010000100100001001 G
b11110010110110011011010001011010 F
b1111100100110001110011111101111 E
b11101110101010100110100000011010 C
#1902
b1 9
b1 K
b1 8
b1 L
b110001 6
b110001 N
b1 7
b1 M
0#
1'
b1110 5
b1110 O
b10 =
b10 `
b1110 3
b1110 [
b110010 :
b110010 ]
b10 <
b10 _
b111110 4
b111110 \
b10 ;
b10 ^
b1 %
b1 R
b0 )
b0 T
b1 "
b1 Q
b0 &
b0 S
1$
0(
b1110 !
b1110 B
b1110 J
b1110 P
#2200
b101 I
#2300
b11000010011101011110111011000011 D
b1111001011010011101100110011110 G
b10010111001011010000100100001001 F
b11110010110110011011010001011010 E
b10111011101001111001111111101111 C
#2302
b1100 9
b1100 K
b1100 8
b1100 L
b111100 6
b111100 N
b111100 7
b111100 M
1#
0'
b11 5
b11 O
b1101 =
b1101 `
b11 3
b11 [
b111101 :
b111101 ]
b1101 <
b1101 _
b11 4
b11 \
b111101 ;
b111101 ^
b0 %
b0 R
b1 )
b1 T
b0 "
b0 Q
b1 &
b1 S
0$
1(
b11 !
b11 B
b11 J
b11 P
#2600
b110 I
#2700
b11111101001100011110100110110011 D
b11000010011101011110111011000011 G
b1111001011010011101100110011110 F
b10010111001011010000100100001001 E
b111111011110110110010001011010 C
#3000
b111 I
#3100
b10101010111101001001011101 D
b11111101001100011110100110110011 G
b11000010011101011110111011000011 F
b1111001011010011101100110011110 E
b11111111011001010100000100001001 C
#3102
b10 9
b10 K
b10 8
b10 L
b110010 6
b110010 N
b10 7
b10 M
b1101 5
b1101 O
b11 =
b11 `
b1101 3
b1101 [
b110011 :
b110011 ]
b11 <
b11 _
b111101 4
b111101 \
b11 ;
b11 ^
b1 %
b1 R
b0 )
b0 T
b1 "
b1 Q
b0 &
b0 S
1$
0(
b1101 !
b1101 B
b1101 J
b1101 P
#3400
b1000 I
#3500
b110101001110010101111010111111 D
b10101010111101001001011101 G
b11111101001100011110100110110011 F
b11000010011101011110111011000011 E
b110111101001010010100110011110 C
#3502
b0 9
b0 K
b0 8
b0 L
b110000 6
b110000 N
b0 7
b0 M
b1111 5
b1111 O
b1 =
b1 `
b1111 3
b1111 [
b110001 :
b110001 ]
b1 <
b1 _
b111111 4
b111111 \
b1 ;
b1 ^
b1 2
b1 Z
b0 %
b0 R
b1 )
b1 T
b1 0
b1 Y
b0 "
b0 Q
b1 &
b1 S
11
0$
1(
b1111 !
b1111 B
b1111 J
b1111 P
#3800
b1001 I
#3900
b1011000010101111010110100101101 D
b110101001110010101111010111111 G
b10101010111101001001011101 F
b11111101001100011110100110110011 E
b1101101000000111111011011000011 C
#3902
b10 9
b10 K
b10 8
b10 L
b110010 6
b110010 N
b10 7
b10 M
b1101 5
b1101 O
b11 =
b11 `
b1101 3
b1101 [
b110011 :
b110011 ]
b11 <
b11 _
b111101 4
b111101 \
b11 ;
b11 ^
b0 2
b0 Z
b1 %
b1 R
b0 )
b0 T
b0 0
b0 Y
b1 "
b1 Q
b0 &
b0 S
01
1$
0(
b1101 !
b1101 B
b1101 J
b1101 P
#4200
b1010 I
#4300
b101010010110011010101111100101 D
b1011000010101111010110100101101 G
b110101001110010101111010111111 F
b10101010111101001001011101 E
b1110010011111000111000110110011 C
#4302
b1010 9
b1010 K
b1010 8
b1010 L
b111010 6
b111010 N
b111010 7
b111010 M
b101 5
b101 O
b1011 =
b1011 `
b101 3
b101 [
b111011 :
b111011 ]
b1011 <
b1011 _
b101 4
b101 \
b111011 ;
b111011 ^
b0 %
b0 R
b1 )
b1 T
b0 "
b0 Q
b1 &
b1 S
0$
1(
b101 !
b101 B
b101 J
b101 P
#4600
b1011 I
#4700
b1110110001111001010110111001001 D
b101010010110011010101111100101 G
b1011000010101111010110100101101 F
b110101001110010101111010111111 E
b1011100001110010011101001011101 C
#4702
b110 9
b110 K
b110 8
b110 L
b110110 6
b110110 N
b110 7
b110 M
b1001 5
b1001 O
b111 =
b111 `
b1001 3
b1001 [
b110111 :
b110111 ]
b111 <
b111 _
b111001 4
b111001 \
b111 ;
b111 ^
b1001 !
b1001 B
b1001 J
b1001 P
#5000
b1100 I
#5100
b10001001000011111100100100010111 D
b1110110001111001010110111001001 G
b101010010110011010101111100101 F
b1011000010101111010110100101101 E
b11111111110011001010011010111111 C
#5102
b1000 9
b1000 K
b1000 8
b1000 L
b111000 6
b111000 N
b111000 7
b111000 M
b111 5
b111 O
b1001 =
b1001 `
b111 3
b111 [
b111001 :
b111001 ]
b1001 <
b1001 _
b111 4
b111 \
b111001 ;
b111001 ^
b1 %
b1 R
b0 )
b0 T
b1 "
b1 Q
b0 &
b0 S
1$
0(
b111 !
b111 B
b111 J
b111 P
#5400
b1101 I
#5500
b1101100110101000010001111011110 D
b10001001000011111100100100010111 G
b1110110001111001010110111001001 F
b101010010110011010101111100101 E
b11100101001111101100010100101101 C
#5502
b1 9
b1 K
b1 8
b1 L
b110001 6
b110001 N
b1 7
b1 M
0#
1'
b1110 5
b1110 O
b10 =
b10 `
b1110 3
b1110 [
b110010 :
b110010 ]
b10 <
b10 _
b111110 4
b111110 \
b10 ;
b10 ^
b1110 !
b1110 B
b1110 J
b1110 P
#5800
b1110 I
#5900
b10001011001101011010101100100010 D
b1101100110101000010001111011110 G
b10001001000011111100100100010111 F
b1110110001111001010110111001001 E
b11100111000001101000001111100101 C
#5902
b1101 9
b1101 K
b1101 8
b1101 L
b111101 6
b111101 N
b111101 7
b111101 M
b10 5
b10 O
b1110 =
b1110 `
b10 3
b10 [
b111110 :
b111110 ]
b1110 <
b1110 _
b10 4
b10 \
b111110 ;
b111110 ^
b10 !
b10 B
b10 J
b10 P
#6200
b1111 I
#6300
b11000111101000000110101101000 D
b10001011001101011010101100100010 G
b1101100110101000010001111011110 F
b10001001000011111100100100010111 E
b10010011010100101110010111001001 C
#6302
b111 9
b111 K
b111 8
b111 L
b110111 6
b110111 N
b111 7
b111 M
b1000 5
b1000 O
b1000 =
b1000 `
b1000 3
b1000 [
b111000 :
b111000 ]
b1000 <
b1000 _
b111000 4
b111000 \
b1000 ;
b1000 ^
b1000 !
b1000 B
b1000 J
b1000 P
#6600
b10000 I
#6700
b11101111010001000011100000010000 D
b11000111101000000110101101000 G
b10001011001101011010101100100010 F
b1101100110101000010001111011110 E
b11110111010001110111000100010111 C
#6702
b1111 9
b1111 K
b1111 8
b1111 L
b111111 6
b111111 N
b111111 7
b111111 M
b0 /
b0 X
b1 @
b1 b
b0 -
b0 W
b1 >
b1 a
0.
1?
b0 5
b0 O
b0 =
b0 `
b0 3
b0 [
b0 :
b0 ]
b0 <
b0 _
b0 4
b0 \
b0 ;
b0 ^
b0 ,
b0 V
b0 %
b0 R
b1 )
b1 T
b0 *
b0 U
b0 "
b0 Q
b1 &
b1 S
0+
0$
1(
b0 !
b0 B
b0 J
b0 P
#7000
b10001 I
#7100
b100010010000110011110011110101 D
b11101111010001000011100000010000 G
b11000111101000000110101101000 F
b10001011001101011010101100100010 E
b11001101110010101101001111011110 C
#7102
b1010 9
b1010 K
b1010 8
b1010 L
b111010 6
b111010 N
b111010 7
b111010 M
b1 /
b1 X
b0 @
b0 b
b1 -
b1 W
b0 >
b0 a
1.
0?
1#
0'
b101 5
b101 O
b1011 =
b1011 `
b101 3
b101 [
b111011 :
b111011 ]
b1011 <
b1011 _
b101 4
b101 \
b111011 ;
b111011 ^
b1 ,
b1 V
b1 *
b1 U
1+
b101 !
b101 B
b101 J
b101 P
#7400
b10010 I
#7500
b100000010011110111100100100 D
b100010010000110011110011110101 G
b11101111010001000011100000010000 F
b11000111101000000110101101000 E
b100110011011001011101100100010 C
#7502
b1011 9
b1011 K
b1011 8
b1011 L
b111011 6
b111011 N
b111011 7
b111011 M
0#
1'
b100 5
b100 O
b1100 =
b1100 `
b100 3
b100 [
b111100 :
b111100 ]
b1100 <
b1100 _
b100 4
b100 \
b111100 ;
b111100 ^
b1 %
b1 R
b0 )
b0 T
b1 "
b1 Q
b0 &
b0 S
1$
0(
b100 !
b100 B
b100 J
b100 P
#7800
b10011 I
#7900
b10111100001011100011110110000000 D
b100000010011110111100100100 G
b100010010000110011110011110101 F
b11101111010001000011100000010000 E
b10111000100111110100110101101000 C
#7902
b1111 9
b1111 K
b1111 8
b1111 L
b111111 6
b111111 N
b111111 7
b111111 M
b0 /
b0 X
b1 @
b1 b
b0 -
b0 W
b1 >
b1 a
0.
1?
b0 5
b0 O
b0 =
b0 `
b0 3
b0 [
b0 :
b0 ]
b0 <
b0 _
b0 4
b0 \
b0 ;
b0 ^
b0 ,
b0 V
b0 %
b0 R
b1 )
b1 T
b0 *
b0 U
b0 "
b0 Q
b1 &
b1 S
0+
0$
1(
b0 !
b0 B
b0 J
b0 P
#8200
b10100 I
#8300
b1110010011001000001011010101101 D
b10111100001011100011110110000000 G
b100000010011110111100100100 F
b100010010000110011110011110101 E
b11001110100001001011100000010000 C
#8302
b10 9
b10 K
b10 8
b10 L
b110010 6
b110010 N
b10 7
b10 M
b1 /
b1 X
b0 @
b0 b
b1 -
b1 W
b0 >
b0 a
1.
0?
1#
0'
b1101 5
b1101 O
b11 =
b11 `
b1101 3
b1101 [
b110011 :
b110011 ]
b11 <
b11 _
b111101 4
b111101 \
b11 ;
b11 ^
b1 ,
b1 V
b1 %
b1 R
b0 )
b0 T
b1 *
b1 U
b1 "
b1 Q
b0 &
b0 S
1+
1$
0(
b1101 !
b1101 B
b1101 J
b1101 P
#8600
b10101 I
